edgy/__init__.py
edgy/__main__.py
edgy/_monkay.py
edgy/exceptions.py
edgy/py.typed
edgy/testclient.py
edgy/types.py
edgy/cli/__init__.py
edgy/cli/base.py
edgy/cli/cli.py
edgy/cli/common_params.py
edgy/cli/constants.py
edgy/cli/operations/__init__.py
edgy/cli/operations/admin_serve.py
edgy/cli/operations/branches.py
edgy/cli/operations/check.py
edgy/cli/operations/current.py
edgy/cli/operations/downgrade.py
edgy/cli/operations/edit.py
edgy/cli/operations/heads.py
edgy/cli/operations/history.py
edgy/cli/operations/init.py
edgy/cli/operations/inspectdb.py
edgy/cli/operations/list_templates.py
edgy/cli/operations/makemigrations.py
edgy/cli/operations/merge.py
edgy/cli/operations/migrate.py
edgy/cli/operations/revision.py
edgy/cli/operations/show.py
edgy/cli/operations/stamp.py
edgy/cli/operations/shell/__init__.py
edgy/cli/operations/shell/base.py
edgy/cli/operations/shell/enums.py
edgy/cli/operations/shell/ipython.py
edgy/cli/operations/shell/ptpython.py
edgy/cli/operations/shell/utils.py
edgy/cli/templates/default/README
edgy/cli/templates/default/alembic.ini.mako
edgy/cli/templates/default/env.py
edgy/cli/templates/default/script.py.mako
edgy/cli/templates/plain/README
edgy/cli/templates/plain/alembic.ini.mako
edgy/cli/templates/plain/env.py
edgy/cli/templates/plain/script.py.mako
edgy/cli/templates/sequencial/README
edgy/cli/templates/sequencial/alembic.ini.mako
edgy/cli/templates/sequencial/env.py
edgy/cli/templates/sequencial/generator.py
edgy/cli/templates/sequencial/script.py.mako
edgy/cli/templates/url/README
edgy/cli/templates/url/alembic.ini.mako
edgy/cli/templates/url/env.py
edgy/cli/templates/url/script.py.mako
edgy/conf/__init__.py
edgy/conf/enums.py
edgy/conf/global_settings.py
edgy/conf/module_import.py
edgy/contrib/__init__.py
edgy/contrib/admin/__init__.py
edgy/contrib/admin/application.py
edgy/contrib/admin/config.py
edgy/contrib/admin/mixins.py
edgy/contrib/admin/permissions.py
edgy/contrib/admin/views.py
edgy-0.35.0.dist-info/METADATA
edgy-0.35.0.dist-info/WHEEL
edgy-0.35.0.dist-info/entry_points.txt
edgy-0.35.0.dist-info/licenses/LICENSE
edgy-0.35.0.dist-info/RECORD
