Metadata-Version: 2.4
Name: edgy
Version: 0.35.0
Summary: 🔥 The perfect ORM to work with complex databases 🔥
Project-URL: Homepage, https://github.com/dymmond/edgy
Project-URL: Documentation, https://edgy.dymmond.com
Project-URL: Changelog, https://edgy.dymmond.com/release-notes/
Project-URL: Funding, https://github.com/sponsors/tarsil
Project-URL: Source, https://github.com/dymmond/edgy
Author-email: Tiago Silva <tiago.arasilva@gmail.com>
License-File: LICENSE
Keywords: api,asgi,esmerald,fastapi,framework,http,orm,pydantic,rest,starlette
Classifier: Development Status :: 5 - Production/Stable
Classifier: Environment :: Console
Classifier: Environment :: Other Environment
Classifier: Environment :: Web Environment
Classifier: Framework :: AnyIO
Classifier: Framework :: AsyncIO
Classifier: Intended Audience :: Developers
Classifier: Intended Audience :: Information Technology
Classifier: Intended Audience :: System Administrators
Classifier: License :: OSI Approved :: BSD License
Classifier: Operating System :: OS Independent
Classifier: Programming Language :: Python
Classifier: Programming Language :: Python :: 3
Classifier: Programming Language :: Python :: 3 :: Only
Classifier: Programming Language :: Python :: 3.9
Classifier: Programming Language :: Python :: 3.10
Classifier: Programming Language :: Python :: 3.11
Classifier: Programming Language :: Python :: 3.12
Classifier: Programming Language :: Python :: 3.13
Classifier: Programming Language :: Python :: 3.14
Classifier: Topic :: Database
Classifier: Topic :: Software Development
Classifier: Topic :: Software Development :: Libraries
Classifier: Topic :: Software Development :: Libraries :: Application Frameworks
Classifier: Topic :: Software Development :: Libraries :: Python Modules
Classifier: Typing :: Typed
Requires-Python: >=3.10
Requires-Dist: alembic<2.0.0,>=1.11.3
Requires-Dist: blinker<2.0,>=1.8
Requires-Dist: databasez>=0.10.3
Requires-Dist: monkay>=0.5.0
Requires-Dist: orjson>=3.6.1
Requires-Dist: pydantic-settings<3.0.0,>=2.0.0
Requires-Dist: pydantic[email]<3.0.0,>=2.5.3
Requires-Dist: sayer>=0.7.0
Requires-Dist: typing-extensions>=4.0; python_version < '3.11'
Provides-Extra: admin
Requires-Dist: itsdangerous; extra == 'admin'
Requires-Dist: jinja2; extra == 'admin'
Requires-Dist: lilya>=0.16.7; extra == 'admin'
Requires-Dist: python-multipart; extra == 'admin'
Requires-Dist: uvicorn; extra == 'admin'
Provides-Extra: all
Requires-Dist: databasez[aioodbc]; extra == 'all'
Requires-Dist: databasez[jdbc]; extra == 'all'
Requires-Dist: databasez[mysql]; extra == 'all'
Requires-Dist: databasez[postgresql]; extra == 'all'
Requires-Dist: databasez[sqlite]; extra == 'all'
Requires-Dist: faker>=33.3.1; extra == 'all'
Requires-Dist: ipython; extra == 'all'
Requires-Dist: itsdangerous; extra == 'all'
Requires-Dist: jinja2; extra == 'all'
Requires-Dist: lilya>=0.16.7; extra == 'all'
Requires-Dist: pillow; extra == 'all'
Requires-Dist: ptpython; extra == 'all'
Requires-Dist: python-magic; extra == 'all'
Requires-Dist: python-multipart; extra == 'all'
Requires-Dist: sqlalchemy-utils>=0.41.1; extra == 'all'
Requires-Dist: uvicorn; extra == 'all'
Provides-Extra: image
Requires-Dist: pillow; extra == 'image'
Provides-Extra: jdbc
Requires-Dist: databasez[jdbc]; extra == 'jdbc'
Provides-Extra: mime
Requires-Dist: python-magic; extra == 'mime'
Provides-Extra: mssql
Requires-Dist: databasez[aioodbc]; extra == 'mssql'
Provides-Extra: mysql
Requires-Dist: databasez[mysql]; extra == 'mysql'
Provides-Extra: postgres
Requires-Dist: databasez[postgresql]; extra == 'postgres'
Provides-Extra: sqlite
Requires-Dist: databasez[sqlite]; extra == 'sqlite'
Provides-Extra: test
Requires-Dist: faker>=33.3.1; extra == 'test'
Requires-Dist: sqlalchemy-utils>=0.41.1; extra == 'test'
Provides-Extra: testing
Requires-Dist: anyio<5,>=4.0.0; extra == 'testing'
Requires-Dist: asyncpg<1,>=0.27.0; extra == 'testing'
Requires-Dist: esmerald[standard,test]>=3.2.0; extra == 'testing'
Requires-Dist: httpx; extra == 'testing'
Requires-Dist: ipdb; extra == 'testing'
Requires-Dist: mypy[faster-cache]<2.0,>=1.16; extra == 'testing'
Requires-Dist: ordered-set; extra == 'testing'
Requires-Dist: pytest-mock; extra == 'testing'
Requires-Dist: pytest-timeout; extra == 'testing'
Requires-Dist: uvicorn; extra == 'testing'
Provides-Extra: types
